odoo9_addon_mail_environment-9.0.1.0.0.99.dev15-py2.7-nspkg.pth
odoo9_addon_mail_environment-9.0.1.0.0.99.dev15.dist-info/METADATA
odoo9_addon_mail_environment-9.0.1.0.0.99.dev15.dist-info/RECORD
odoo9_addon_mail_environment-9.0.1.0.0.99.dev15.dist-info/WHEEL
odoo9_addon_mail_environment-9.0.1.0.0.99.dev15.dist-info/namespace_packages.txt
odoo9_addon_mail_environment-9.0.1.0.0.99.dev15.dist-info/top_level.txt
odoo_addons/mail_environment/README.rst
odoo_addons/mail_environment/__init__.py
odoo_addons/mail_environment/__openerp__.py
odoo_addons/mail_environment/env_mail.py
odoo_addons/mail_environment/mail_view.xml
odoo_addons/mail_environment/i18n/ca.po
odoo_addons/mail_environment/i18n/de.po
odoo_addons/mail_environment/i18n/es.po
odoo_addons/mail_environment/i18n/hr.po
odoo_addons/mail_environment/i18n/mail_environment.pot
odoo_addons/mail_environment/i18n/pt_BR.po
odoo_addons/mail_environment/i18n/sl.po
odoo_addons/mail_environment/i18n/zh_CN.po
odoo_addons/mail_environment/static/description/icon.png
